setup.py
pumpr/__init__.py
pumpr/__main__.py
pumpr/cli.py
pumpr/config.py
pumpr/pumpr.py
pumpr.egg-info/PKG-INFO
pumpr.egg-info/SOURCES.txt
pumpr.egg-info/dependency_links.txt
pumpr.egg-info/entry_points.txt
pumpr.egg-info/requires.txt
pumpr.egg-info/top_level.txt