Metadata-Version: 1.0
Name: pumpr
Version: 0.1.0
Summary: Fills syringepump.com syringes with water so you don't have to
Home-page: http://seetravisblog.com
Author: Travis Chapman
Author-email: travisechapman@gmail.com
License: UNKNOWN
Platform: UNKNOWN
